setup.py
signal.py
micropython_signal.egg-info/PKG-INFO
micropython_signal.egg-info/SOURCES.txt
micropython_signal.egg-info/dependency_links.txt
micropython_signal.egg-info/requires.txt
micropython_signal.egg-info/top_level.txt